html2pic/__init__.py
html2pic/exceptions.py
html2pic/html2pic.py
html2pic/dom/__init__.py
html2pic/dom/dom_node.py
html2pic/dom/node_type.py
html2pic/fonts/__init__.py
html2pic/fonts/font_face.py
html2pic/fonts/font_registry.py
html2pic/fonts/font_src_parser.py
html2pic/parsing/__init__.py
html2pic/parsing/css_parser.py
html2pic/parsing/css_rule.py
html2pic/parsing/html_parser.py
html2pic/parsing/selector.py
html2pic/parsing/shorthand_expander.py
html2pic/styling/__init__.py
html2pic/styling/cascade_resolver.py
html2pic/styling/color_normalizer.py
html2pic/styling/default_styles.py
html2pic/styling/style_engine.py
html2pic/styling/unit_converter.py
html2pic/translation/__init__.py
html2pic/translation/element_factory.py
html2pic/translation/shadow_parser.py
html2pic/translation/translator.py
html2pic/translation/value_parsers.py
html2pic/translation/style_applicators/__init__.py
html2pic/translation/style_applicators/background_applicator.py
html2pic/translation/style_applicators/base_applicator.py
html2pic/translation/style_applicators/border_applicator.py
html2pic/translation/style_applicators/layout_applicator.py
html2pic/translation/style_applicators/positioning_applicator.py
html2pic/translation/style_applicators/shadow_applicator.py
html2pic/translation/style_applicators/size_applicator.py
html2pic/translation/style_applicators/spacing_applicator.py
html2pic/translation/style_applicators/transform_applicator.py
html2pic/translation/style_applicators/typography_applicator.py
html2pic/warnings/__init__.py
html2pic/warnings/warning_category.py
html2pic/warnings/warning_collector.py
html2pic-0.2.1.dist-info/METADATA
html2pic-0.2.1.dist-info/WHEEL
html2pic-0.2.1.dist-info/RECORD
