Metadata-Version: 2.4
Name: html2pic
Version: 0.2.1
Summary: Convert HTML + CSS to images without a browser
Project-URL: Homepage, https://github.com/francozanardi/html2pic
Project-URL: Repository, https://github.com/francozanardi/html2pic.git
Project-URL: Bug Tracker, https://github.com/francozanardi/html2pic/issues
Project-URL: Documentation, https://github.com/francozanardi/html2pic/blob/main/README.md
Project-URL: Examples, https://github.com/francozanardi/html2pic/tree/main/examples
Author-email: Franco Zanardi <francozanardi97@gmail.com>
License-Expression: MIT
Keywords: conversion,css,html,image,rendering
Classifier: Development Status :: 3 - Alpha
Classifier: Intended Audience :: Developers
Classifier: License :: OSI Approved :: MIT License
Classifier: Operating System :: OS Independent
Classifier: Programming Language :: Python :: 3
Classifier: Programming Language :: Python :: 3.8
Classifier: Programming Language :: Python :: 3.9
Classifier: Programming Language :: Python :: 3.10
Classifier: Programming Language :: Python :: 3.11
Classifier: Programming Language :: Python :: 3.12
Classifier: Topic :: Multimedia :: Graphics :: Graphics Conversion
Classifier: Topic :: Software Development :: Libraries :: Python Modules
Classifier: Topic :: Text Processing :: Markup :: HTML
Requires-Python: >=3.8
Requires-Dist: beautifulsoup4>=4.9.0
Requires-Dist: pictex>=2.0.0
Requires-Dist: tinycss2>=1.1.0
Provides-Extra: examples
Requires-Dist: pillow>=8.0.0; extra == 'examples'
